pygoml/__init__.py
pygoml-0.0.1.dist-info/LICENSE
pygoml-0.0.1.dist-info/METADATA
pygoml-0.0.1.dist-info/WHEEL
pygoml-0.0.1.dist-info/top_level.txt
pygoml-0.0.1.dist-info/RECORD
